{
  "Laboratorio — Hematología y Coagulación": [
    "Hemograma completo automatizado",
    "Hemoglobina y Hematocrito",
    "Recuento de Plaquetas",
    "Frotis de Sangre Periférica",
    "Reticulocitos",
    "Velocidad de Sedimentación Globular (VSG)",
    "Perfil de Coagulación (TP, TPT, Fibrinógeno, INR)",
    "Tiempo de Protrombina (TP)",
    "Tiempo de Tromboplastina Parcial (TTP)",
    "Tiempo de Trombina",
    "Tiempo de Sangría y Coagulación",
    "Anticoagulante Lúpico",
    "D-Dímero",
    "Ferritina sérica",
    "Hierro sérico",
    "Capacidad Total de Fijación de Hierro (TIBC)",
    "Transferrina / % de Saturación",
    "Vitamina B12 (Cobalamina)",
    "Ácido Fólico (Folato sérico / intraeritrocitario)",
    "Prueba de Coombs Directo",
    "Prueba de Coombs Indirecto",
    "Grupo Sanguíneo y Factor Rh",
    "Gota Gruesa (Hemoparásitos)",
    "Cadenas Ligeras Kappa y Lambda (Suero / Orina)"
  ],
  "Laboratorio — Bioquímica y Electrolitos": [
    "Glucosa en ayunas",
    "Glucosa postprandial (2 horas)",
    "Tolerancia a la Glucosa (Prueba de 75g)",
    "Hemoglobina Glicosilada (HbA1c)",
    "Urea en sangre",
    "Creatinina en sangre",
    "Depuración de Creatinina (Orina 24h)",
    "Ácido Úrico en sangre / orina 24h",
    "Perfil Lipídico completo (Colesterol Total, HDL, LDL, VLDL, Triglicéridos)",
    "Colesterol Total",
    "Colesterol HDL",
    "Colesterol LDL",
    "Triglicéridos",
    "Perfil Hepático (TGO, TGP, Bilirrubinas, GGT, Fosfatasa Alcalina, Albúmina)",
    "Transaminasa TGO (AST)",
    "Transaminasa TGP (ALT)",
    "Bilirrubinas Totales y Fraccionadas (Directa e Indirecta)",
    "Gamma Glutamil Transpeptidasa (GGTP / GGT)",
    "Fosfatasa Alcalina (FA)",
    "Albúmina y Proteínas Totales",
    "Electrolitos Séricos (Sodio, Potasio, Cloro)",
    "Sodio (Na) en suero / orina",
    "Potasio (K) en suero / orina",
    "Cloro (Cl) en suero / orina",
    "Calcio sérico / iónico / orina 24h",
    "Fósforo en sangre / orina",
    "Magnesio en sangre",
    "Amilasa en suero / orina",
    "Lipasa en suero",
    "Deshidrogenasa Láctica (DHL / LDH)",
    "Creatina Fosfocinasa Total (CPK Total)",
    "Creatina Fosfocinasa Fracción MB (CPK-MB)",
    "Troponina I / Troponina T",
    "Procalcitonina (PCT)",
    "Gasometría Arterial (AGA) y Electrolitos"
  ],
  "Laboratorio — Endocrinología y Hormonas": [
    "Perfil Tiroideo I (TSH, T4, T3)",
    "Perfil Tiroideo II (TSH, T4 Libre, T3 Libre, T4, T3)",
    "TSH Ultrasensible",
    "T4 Libre (Tiroxina libre)",
    "T3 Libre (Triyodotironina libre)",
    "T3 Total",
    "T4 Total",
    "Tiroglobulina",
    "Anticuerpos Antitiroideos (Anti-TPO, Anti-Tiroglobulina)",
    "Perfil Hormonal Femenino (FSH, LH, Estradiol, Prolactina, Progesterona)",
    "Hormona Folículo Estimulante (FSH)",
    "Hormona Luteinizante (LH)",
    "Estradiol (E2)",
    "Prolactina (con / sin Pool)",
    "Progesterona",
    "Testosterona Total / Libre",
    "Hormona Antimülleriana (AMH / MIS)",
    "Hormona del Crecimiento (HGH / Somatotropina)",
    "Cortisol AM (Mañana, 8 AM)",
    "Cortisol PM (Tarde, 4 PM)",
    "Cortisol en Orina de 24 horas",
    "Insulina Basal / Postprandial",
    "Índice HOMA (Resistencia a la Insulina)",
    "17-OH Progesterona",
    "Subunidad Beta HCG Cuantitativa (Prueba de Embarazo)",
    "Subunidad Beta HCG Cualitativa",
    "PTH Intacta (Paratohormona)",
    "Vitamina D (25-OH Colecalciferol)",
    "Vitamina D (1,25-DiOH Colecalciferol)",
    "SHBG (Globulina Fijadora de Hormonas Sexuales)",
    "DHEA-S (Dehidroepiandrosterona Sulfato)"
  ],
  "Laboratorio — Inmunología y Serología": [
    "Proteína C Reactiva Cualitativa / Cuantitativa / Ultrasensible (PCR)",
    "Perfil Reumático (FR, PCR, ASO, Ácido Úrico, VSG)",
    "Factor Reumatoide (FR / Latex)",
    "Antiestreptolisina O (ASO)",
    "Anticuerpos Antinucleares (ANA)",
    "Anticuerpos Anti-DNA Nativo (Doble Cadena)",
    "Perfil ENA (Anti-Ro, Anti-La, Anti-Sm, Anti-RNP)",
    "Perfil Antifosfolípido (Anti-Cardiolipina IgG/IgM, Anti-Beta2 Glicoproteína, Anticoagulante Lúpico)",
    "Anticuerpos Anti-Cardiolipina IgG / IgM",
    "ANCA C y ANCA P",
    "Inmunoglobulina A (IgA)",
    "Inmunoglobulina G (IgG)",
    "Inmunoglobulina M (IgM)",
    "Inmunoglobulina E (IgE Total)",
    "Complemento C3 y C4",
    "Aglutinaciones Febriles (Tífico, Paratífico, Brucella)",
    "Reacción de Widal / Rosa de Bengala (Brucelosis)",
    "VDRL / RPR (Descarte de Sífilis)",
    "Prueba Rápida Sífilis",
    "HIV 1/2 Prueba Rápida / ELISA 4ta Generación",
    "Hepatitis B — Antígeno de Superficie (HBsAg)",
    "Hepatitis B — Anticuerpos Core Totales (Anti-HBc)",
    "Hepatitis C — Anticuerpos Totales (Anti-HCV)",
    "Hepatitis A — Anticuerpos IgM (Anti-HAV IgM)",
    "HTLV I/II Anticuerpos",
    "TORCH (Toxoplasma, Rubéola, Citomegalovirus, Herpes I y II)",
    "Toxoplasma gondii IgG / IgM",
    "Citomegalovirus (CMV) IgG / IgM",
    "Rubéola IgG / IgM",
    "Herpes Virus I y II IgG / IgM"
  ],
  "Laboratorio — Microbiología y Cultivos": [
    "BK Directo (Baciloscopía / Esputo)",
    "BK Seriado (3 muestras)",
    "Cultivo de BK (Löwenstein-Jensen)",
    "Urocultivo con Antibiograma",
    "Cultivo de Secreción Vaginal / Cervical con Antibiograma",
    "Cultivo de Secreción Faríngea / Amigdalina",
    "Cultivo de Secreción Ótica / Nasal / Conjuntival",
    "Cultivo de Secreción de Herida / Pus",
    "Hemocultivo (Aerobio / Anaerobio)",
    "Coprocultivo",
    "Cultivo de Hongos (Micológico)",
    "Examen Directo de Hongos (KOH / Frotis)",
    "Cultivo de Esperma (Espermocultivo)",
    "Prueba Molecular RT-PCR COVID-19",
    "Antígeno Nasofaríngeo COVID-19 / Influenza A y B"
  ],
  "Laboratorio — Parasitología y Uroanálisis": [
    "Examen Completo de Orina (Físico, Químico y Sedimento)",
    "Microalbuminuria en Orina Simple / 24 horas",
    "Proteinuria en Orina de 24 horas",
    "Parasitológico Simple en Heces (1 muestra)",
    "Parasitológico Seriado en Heces (3 muestras)",
    "Coprológico Funcional (pH, azúcares reductores, grasas, sangre)",
    "Reacción Inflamatoria en Heces (Leucocitos)",
    "Sangre Oculta en Heces (Thevenon / Inmunológico)",
    "Test de Graham (Oxiuros)",
    "Antígeno Fecal Helicobacter Pylori",
    "Test de Aliento para Helicobacter Pylori (Ureasa)"
  ],
  "Laboratorio — Marcadores Tumorales y Genética": [
    "PSA Total (Antígeno Prostático Específico)",
    "PSA Libre e Índice PSA",
    "CEA (Antígeno Carcinoembrionario)",
    "CA-125 (Ovario)",
    "CA 15-3 (Mama)",
    "CA 19-9 (Páncreas / Gastrointestinal)",
    "CA 72-4 (Estómago)",
    "Alfa-Fetoproteína (AFP)",
    "Calcitonina",
    "Cromogranina A",
    "Beta-2 Microglobulina",
    "Cariotipo en Sangre Periférica / Médula Ósea"
  ],
  "Laboratorio — Dosaje de Medicamentos y Toxicología": [
    "Dosaje de Ácido Valproico",
    "Dosaje de Carbamazepina",
    "Dosaje de Fenitoína (Difenilhidantoína)",
    "Dosaje de Fenobarbital",
    "Dosaje de Litio",
    "Dosaje de Digoxina",
    "Dosaje de Teofilina",
    "Screening Toxicológico en Orina (Marihuana, Cocaína, Anfetaminas, Benzodiazepinas)"
  ],
  "Laboratorio — Anatomía Patológica y Citología": [
    "Papanicolaou (PAP) Convencional de Cérvix",
    "Citología en Base Líquida de Cérvix",
    "Biopsia Chica (Piel, Cuello Uterino, Gástrica, Próstata)",
    "Biopsia Mediana / Grande (Pieza Quirúrgica)",
    "Revisión de Láminas y Bloques de Parafina",
    "Bloque Celular / Citología de Líquidos",
    "Estudio Inmunohistoquímico"
  ],
  "Ecografías": [
    "Ecografía abdominal completa",
    "Ecografía abdominal superior",
    "Ecografía articular",
    "Ecografía cerebral transfontanelar",
    "Ecografía de cadera (displasia infantil)",
    "Ecografía de glándulas salivales",
    "Ecografía de mamas",
    "Ecografía de partes blandas",
    "Ecografía de pared abdominal",
    "Ecografía de tiroides y paratiroides",
    "Ecografía Doppler arterial de miembros inferiores",
    "Ecografía Doppler arterial de miembros superiores",
    "Ecografía Doppler carotídeo y vertebral",
    "Ecografía Doppler renal",
    "Ecografía Doppler venoso de miembros inferiores",
    "Ecografía Doppler venoso de miembros superiores",
    "Ecografía ginecológica",
    "Ecografía hepática y de vías biliares",
    "Ecografía inguinal (hernias)",
    "Ecografía obstétrica",
    "Ecografía obstétrica con perfil biofísico",
    "Ecografía obstétrica Doppler",
    "Ecografía obstétrica morfológica",
    "Ecografía pélvica",
    "Ecografía prostática transabdominal",
    "Ecografía prostática transrectal",
    "Ecografía renal y de vías urinarias",
    "Ecografía testicular / escrotal",
    "Ecografía transvaginal"
  ],
  "Estudios Especiales": [
    "Densitometría ósea (DEXA)",
    "Elastografía de transición hepática (Fibroscan)",
    "Mamografía bilateral"
  ],
  "Rayos X": [
    "Radiografía de abdomen simple",
    "Radiografía de abdomen (de pie y decúbito)",
    "Radiografía de cadera",
    "Radiografía de codo",
    "Radiografía de columna cervical",
    "Radiografía de columna dorsal",
    "Radiografía de columna lumbar",
    "Radiografía de columna lumbosacra",
    "Radiografía de cráneo",
    "Radiografía de fémur",
    "Radiografía de hombro",
    "Radiografía de mano",
    "Radiografía de muñeca",
    "Radiografía de pelvis",
    "Radiografía de pie",
    "Radiografía de rodilla",
    "Radiografía de senos paranasales",
    "Radiografía de tobillo",
    "Radiografía de tórax (PA y lateral)",
    "Serie ósea metastásica"
  ],
  "Resonancias Magnéticas (RM)": [
    "Resonancia magnética de abdomen con contraste",
    "Resonancia magnética de abdomen sin contraste",
    "Resonancia magnética de cerebro con contraste",
    "Resonancia magnética de cerebro sin contraste",
    "Resonancia magnética de columna cervical con contraste",
    "Resonancia magnética de columna cervical sin contraste",
    "Resonancia magnética de columna lumbar con contraste",
    "Resonancia magnética de columna lumbar sin contraste",
    "Resonancia magnética de hombro",
    "Resonancia magnética de pelvis",
    "Resonancia magnética de rodilla",
    "Colangiorresonancia magnética (colangio-RM)"
  ],
  "Tomografías Computarizadas (TC)": [
    "Tomografía computarizada de abdomen y pelvis con contraste",
    "Tomografía computarizada de abdomen y pelvis sin contraste",
    "Tomografía computarizada de cerebro con contraste",
    "Tomografía computarizada de cerebro sin contraste",
    "Tomografía computarizada de columna lumbar",
    "Tomografía computarizada de senos paranasales",
    "Tomografía computarizada de tórax con contraste",
    "Tomografía computarizada de tórax sin contraste",
    "Uro-TC (tomografía de vías urinarias)",
    "Angio-TC de tórax"
  ]
}
